[{"name":"Saffron","users":["92mwfTrtfSRsiOzcahAIKsNW5vO2","BnwWAepzt0NMd880xRNNvEOjxnv2","PCKjaUvI9caAgoRZTuQYvjRirCl1","y0Vb464iCdeVzfBJBZzCjCIZIi72","XYkYvhODvjg1pLVfqtFXAGZxuCj1"],"id":"40oJ7dA8bIj3OTqFSONU","points":{"streak":0,"total":0}},{"points":{"streak":0,"total":0},"id":"HCIp64TZWZc08WvJBlJW","users":["aWI6X9i1RugALHJ7ILr8Xp4baIW2","amN2Z3FGaTQnjwSktECXoGYXEYi1","bksg6W8mYZamOArxMiK2pn3UlGe2","qBHCpnXFOLZsdzcHbKzvkqP6Uck1","lMl7YkcHrzSQnR4di8OJsDVmeEC3"],"name":"Celadon"},{"name":"Vermillion","users":["8O6cHx6IxmTUXaMnXhxcQ2HFgEV2","B762i26QM7Y275I0w2uAtklg3Gx1","VsNPZ5xdDgdZxTUeynrJJk5Qs5v2","ZJTGuZOOvgaIycOFMIq2vSXXD292","tRLVcXr9ZXgF3A5VzwO4rrESCY32"],"id":"NtcoKXuizm03YrYaUKsz","points":{"total":0,"streak":0}},{"points":{"season":0,"total":0},"id":"ifqU2lIIe8tTWm2QACh0","name":"Lavender","users":["1at5cLzMWad6Kb4bXJGzbuCIe383","8d5n92IZsOMbZtnfoEgMhjFF8C63","btmzQ2h02aa7NwgpOFMGvGSgcv62","GxloHn9wFkRFYYHXSuTj56kXd0q2","SMJFRAatZgXUeXXcx2ijheHyBqv1"]}]